{
  "project_info": {
    "project_number": "704479136362",
    "firebase_url": "https://fcmtest-670f6.firebaseio.com",
    "project_id": "fcmtest-670f6",
    "storage_bucket": "fcmtest-670f6.appspot.com"
  },
  "client": [
    {
      "client_info": {
        "mobilesdk_app_id": "1:704479136362:android:daeafbcc9c25e23d",
        "android_client_info": {
          "package_name": "io.cordova.toeicmanager"
        }
      },
      "oauth_client": [
        {
          "client_id": "704479136362-pgc0d5vb6r6vnrhqm6livd022vv3atf4.apps.googleusercontent.com",
          "client_type": 3
        }
      ],
      "api_key": [
        {
          "current_key": "AIzaSyAv9AiA_5WhpKVQGOk9aTKFqGavgrBxsKA"
        }
      ],
      "services": {
        "analytics_service": {
          "status": 1
        },
        "appinvite_service": {
          "status": 1,
          "other_platform_oauth_client": []
        },
        "ads_service": {
          "status": 2
        }
      }
    }
  ],
  "configuration_version": "1"
}